everon/__init__.py
everon/__version__.py
everon/core.py
everon-0.0.1.dist-info/LICENSE
everon-0.0.1.dist-info/METADATA
everon-0.0.1.dist-info/WHEEL
everon-0.0.1.dist-info/top_level.txt
everon-0.0.1.dist-info/RECORD
