Metadata-Version: 2.1
Name: everon
Version: 0.0.1
Summary: It makes easier to build user command-line interface
Home-page: https://github.com/wayfar3/everon
Author: Victor Dao
Author-email: daongocthang.vn@gmail.com
License: MIT
Platform: UNKNOWN
Classifier: License :: OSI Approved :: MIT License
Classifier: Operating System :: OS Independent
Classifier: Programming Language :: Python :: 3
Classifier: Programming Language :: Python :: 3.4
Classifier: Programming Language :: Python :: 3.5
Classifier: Programming Language :: Python :: 3.6
Classifier: Programming Language :: Python :: 3.7
Requires-Dist: colorama
